<?xml version="1.0" encoding="UTF-8"?><record_update table="sp_instance">
    <sp_instance action="DELETE">
        <active>true</active>
        <class_name/>
        <color>default</color>
        <css/>
        <glyph/>
        <id/>
        <order>1</order>
        <roles/>
        <short_description/>
        <size>md</size>
        <sp_column display_value="1">fc3e86cd2f1310108631f7ecf699b6d5</sp_column>
        <sp_widget display_value="Form">fd1f4ec347730200ba13a5554ee490c0</sp_widget>
        <sys_class_name>sp_instance</sys_class_name>
        <sys_created_by>admin</sys_created_by>
        <sys_created_on>2020-09-15 09:29:15</sys_created_on>
        <sys_id>664e428d2f1310108631f7ecf699b684</sys_id>
        <sys_mod_count>4</sys_mod_count>
        <sys_name/>
        <sys_package display_value="ReisekostenabrechnungGr7" source="x_526619_reisekost">e45451372f031010e4c854492799b62b</sys_package>
        <sys_policy/>
        <sys_scope display_value="ReisekostenabrechnungGr7">e45451372f031010e4c854492799b62b</sys_scope>
        <sys_update_name>sp_instance_664e428d2f1310108631f7ecf699b684</sys_update_name>
        <sys_updated_by>admin</sys_updated_by>
        <sys_updated_on>2020-09-15 09:29:39</sys_updated_on>
        <title/>
        <url/>
        <widget_parameters><![CDATA[{
	"disableUIActions": {
		"value": "false",
		"displayValue": "false"
	},
	"showFormView": {
		"value": "false",
		"displayValue": "false"
	},
	"omitHeaderOptions": {
		"value": "false",
		"displayValue": "false"
	}
}]]></widget_parameters>
    </sp_instance>
    <sys_translated_text action="DELETE" query="documentkey=664e428d2f1310108631f7ecf699b684"/>
    <sys_update_version action="INSERT_OR_UPDATE">
        <action>DELETE</action>
        <application display_value="ReisekostenabrechnungGr7">e45451372f031010e4c854492799b62b</application>
        <file_path/>
        <instance_id>10a42f9fdb75c89452dd2f17d49619c2</instance_id>
        <instance_name>dev96488</instance_name>
        <name>sp_instance_664e428d2f1310108631f7ecf699b684</name>
        <payload>&lt;?xml version="1.0" encoding="UTF-8"?&gt;&lt;record_update table="sp_instance"&gt;&lt;sp_instance action="INSERT_OR_UPDATE"&gt;&lt;active&gt;true&lt;/active&gt;&lt;class_name/&gt;&lt;color&gt;default&lt;/color&gt;&lt;css/&gt;&lt;glyph/&gt;&lt;id/&gt;&lt;order&gt;1&lt;/order&gt;&lt;roles/&gt;&lt;short_description/&gt;&lt;size&gt;md&lt;/size&gt;&lt;sp_column display_value="1"&gt;fc3e86cd2f1310108631f7ecf699b6d5&lt;/sp_column&gt;&lt;sp_widget display_value="Form"&gt;fd1f4ec347730200ba13a5554ee490c0&lt;/sp_widget&gt;&lt;sys_class_name&gt;sp_instance&lt;/sys_class_name&gt;&lt;sys_created_by&gt;admin&lt;/sys_created_by&gt;&lt;sys_created_on&gt;2020-09-15 09:29:15&lt;/sys_created_on&gt;&lt;sys_id&gt;664e428d2f1310108631f7ecf699b684&lt;/sys_id&gt;&lt;sys_mod_count&gt;4&lt;/sys_mod_count&gt;&lt;sys_name/&gt;&lt;sys_package display_value="ReisekostenabrechnungGr7" source="x_526619_reisekost"&gt;e45451372f031010e4c854492799b62b&lt;/sys_package&gt;&lt;sys_policy/&gt;&lt;sys_scope display_value="ReisekostenabrechnungGr7"&gt;e45451372f031010e4c854492799b62b&lt;/sys_scope&gt;&lt;sys_update_name&gt;sp_instance_664e428d2f1310108631f7ecf699b684&lt;/sys_update_name&gt;&lt;sys_updated_by&gt;admin&lt;/sys_updated_by&gt;&lt;sys_updated_on&gt;2020-09-15 09:29:39&lt;/sys_updated_on&gt;&lt;title/&gt;&lt;url/&gt;&lt;widget_parameters&gt;&lt;![CDATA[{
	"disableUIActions": {
		"value": "false",
		"displayValue": "false"
	},
	"showFormView": {
		"value": "false",
		"displayValue": "false"
	},
	"omitHeaderOptions": {
		"value": "false",
		"displayValue": "false"
	}
}]]&gt;&lt;/widget_parameters&gt;&lt;/sp_instance&gt;&lt;sys_translated_text action="delete_multiple" query="documentkey=664e428d2f1310108631f7ecf699b684"/&gt;&lt;/record_update&gt;</payload>
        <payload_hash>-1123488968</payload_hash>
        <record_name/>
        <reverted_from/>
        <source>4324bac82f1750108631f7ecf699b68b</source>
        <source_table>sys_update_set</source_table>
        <state>current</state>
        <sys_created_by>admin</sys_created_by>
        <sys_created_on>2020-09-15 09:29:39</sys_created_on>
        <sys_id>946e4e012f5310108631f7ecf699b63b</sys_id>
        <sys_mod_count>0</sys_mod_count>
        <sys_recorded_at>17491192ae10000001</sys_recorded_at>
        <sys_updated_by>admin</sys_updated_by>
        <sys_updated_on>2020-09-15 09:29:39</sys_updated_on>
        <type>Instance</type>
        <update_guid>9c6e4e01be531010abb04360f6d2f03a</update_guid>
        <update_guid_history>9c6e4e01be531010abb04360f6d2f03a:-1123488968,db5e4e01e1531010d512c3abc5b37636:163459370,b95e4ecdad13101069356ff3fa22960b:-2063634262,d05e0acdad131010e5e424cb819e15bf:1650932806,2e4e428dba131010fb090a35620c8585:-1089472188</update_guid_history>
    </sys_update_version>
    <sys_metadata_delete action="INSERT_OR_UPDATE">
        <sys_audit_delete display_value="">37ff4e012f5310108631f7ecf699b67b</sys_audit_delete>
        <sys_class_name>sys_metadata_delete</sys_class_name>
        <sys_created_by>admin</sys_created_by>
        <sys_created_on>2020-09-15 09:36:43</sys_created_on>
        <sys_db_object display_value="" name="sp_instance">sp_instance</sys_db_object>
        <sys_id>122a72f791c74be281df397f1ebf58c1</sys_id>
        <sys_metadata>664e428d2f1310108631f7ecf699b684</sys_metadata>
        <sys_mod_count>0</sys_mod_count>
        <sys_name/>
        <sys_package display_value="ReisekostenabrechnungGr7" source="x_526619_reisekost">e45451372f031010e4c854492799b62b</sys_package>
        <sys_parent/>
        <sys_policy/>
        <sys_scope display_value="ReisekostenabrechnungGr7">e45451372f031010e4c854492799b62b</sys_scope>
        <sys_scope_delete display_value="">28719247fa724b2e8c95e64ffb1c1004</sys_scope_delete>
        <sys_update_name>sp_instance_664e428d2f1310108631f7ecf699b684</sys_update_name>
        <sys_update_version display_value="sp_instance_664e428d2f1310108631f7ecf699b684">946e4e012f5310108631f7ecf699b63b</sys_update_version>
        <sys_updated_by>admin</sys_updated_by>
        <sys_updated_on>2020-09-15 09:36:43</sys_updated_on>
    </sys_metadata_delete>
</record_update>
