<?xml version="1.0" encoding="UTF-8"?><record_update table="sp_instance">
    <sp_instance action="DELETE">
        <active>true</active>
        <class_name/>
        <color>default</color>
        <css/>
        <glyph/>
        <id/>
        <order>1</order>
        <roles/>
        <short_description/>
        <size>md</size>
        <sp_column display_value="1">1b91558e2f5b10108631f7ecf699b6a8</sp_column>
        <sp_widget display_value="Approval Info">33442352cb30020000f8d856634c9c3f</sp_widget>
        <sys_class_name>sp_instance</sys_class_name>
        <sys_created_by>admin</sys_created_by>
        <sys_created_on>2020-09-18 07:44:43</sys_created_on>
        <sys_id>9c23194e2f5b10108631f7ecf699b688</sys_id>
        <sys_mod_count>0</sys_mod_count>
        <sys_name/>
        <sys_package display_value="ReisekostenabrechnungGr7" source="x_526619_reisekost">e45451372f031010e4c854492799b62b</sys_package>
        <sys_policy/>
        <sys_scope display_value="ReisekostenabrechnungGr7">e45451372f031010e4c854492799b62b</sys_scope>
        <sys_update_name>sp_instance_9c23194e2f5b10108631f7ecf699b688</sys_update_name>
        <sys_updated_by>admin</sys_updated_by>
        <sys_updated_on>2020-09-18 07:44:43</sys_updated_on>
        <title/>
        <url/>
        <widget_parameters/>
    </sp_instance>
    <sys_translated_text action="DELETE" query="documentkey=9c23194e2f5b10108631f7ecf699b688"/>
    <sys_update_version action="INSERT_OR_UPDATE">
        <action>DELETE</action>
        <application display_value="ReisekostenabrechnungGr7">e45451372f031010e4c854492799b62b</application>
        <file_path/>
        <instance_id>10a42f9fdb75c89452dd2f17d49619c2</instance_id>
        <instance_name>dev96488</instance_name>
        <name>sp_instance_9c23194e2f5b10108631f7ecf699b688</name>
        <payload><![CDATA[<?xml version="1.0" encoding="UTF-8"?><record_update table="sp_instance"><sp_instance action="INSERT_OR_UPDATE"><active>true</active><class_name/><color>default</color><css/><glyph/><id/><order>1</order><roles/><short_description/><size>md</size><sp_column display_value="1">1b91558e2f5b10108631f7ecf699b6a8</sp_column><sp_widget display_value="Approval Info">33442352cb30020000f8d856634c9c3f</sp_widget><sys_class_name>sp_instance</sys_class_name><sys_created_by>admin</sys_created_by><sys_created_on>2020-09-18 07:44:43</sys_created_on><sys_id>9c23194e2f5b10108631f7ecf699b688</sys_id><sys_mod_count>0</sys_mod_count><sys_name/><sys_package display_value="ReisekostenabrechnungGr7" source="x_526619_reisekost">e45451372f031010e4c854492799b62b</sys_package><sys_policy/><sys_scope display_value="ReisekostenabrechnungGr7">e45451372f031010e4c854492799b62b</sys_scope><sys_update_name>sp_instance_9c23194e2f5b10108631f7ecf699b688</sys_update_name><sys_updated_by>admin</sys_updated_by><sys_updated_on>2020-09-18 07:44:43</sys_updated_on><title/><url/><widget_parameters/></sp_instance><sys_translated_text action="delete_multiple" query="documentkey=9c23194e2f5b10108631f7ecf699b688"/></record_update>]]></payload>
        <payload_hash>804162412</payload_hash>
        <record_name/>
        <reverted_from/>
        <source>3b1210ad2fdf10108631f7ecf699b6af</source>
        <source_table>sys_update_set</source_table>
        <state>previous</state>
        <sys_created_by>admin</sys_created_by>
        <sys_created_on>2020-09-18 07:44:43</sys_created_on>
        <sys_id>9c2315ce2f5b10108631f7ecf699b6c4</sys_id>
        <sys_mod_count>0</sys_mod_count>
        <sys_recorded_at>174a02c2ba90000001</sys_recorded_at>
        <sys_updated_by>admin</sys_updated_by>
        <sys_updated_on>2020-09-18 07:44:43</sys_updated_on>
        <type>Instance</type>
        <update_guid>d42315ce265b1010ba743238c5f4a2c4</update_guid>
        <update_guid_history>d42315ce265b1010ba743238c5f4a2c4:804162412</update_guid_history>
    </sys_update_version>
    <sys_metadata_delete action="INSERT_OR_UPDATE">
        <sys_audit_delete display_value="">7d231d8e2f5b10108631f7ecf699b6db</sys_audit_delete>
        <sys_class_name>sys_metadata_delete</sys_class_name>
        <sys_created_by>admin</sys_created_by>
        <sys_created_on>2020-09-18 07:44:50</sys_created_on>
        <sys_db_object display_value="" name="sp_instance">sp_instance</sys_db_object>
        <sys_id>2dd3688edb024dcfafbb6e0dbd9e37b1</sys_id>
        <sys_metadata>9c23194e2f5b10108631f7ecf699b688</sys_metadata>
        <sys_mod_count>0</sys_mod_count>
        <sys_name/>
        <sys_package display_value="ReisekostenabrechnungGr7" source="x_526619_reisekost">e45451372f031010e4c854492799b62b</sys_package>
        <sys_parent/>
        <sys_policy/>
        <sys_scope display_value="ReisekostenabrechnungGr7">e45451372f031010e4c854492799b62b</sys_scope>
        <sys_scope_delete display_value="">28719247fa724b2e8c95e64ffb1c1004</sys_scope_delete>
        <sys_update_name>sp_instance_9c23194e2f5b10108631f7ecf699b688</sys_update_name>
        <sys_update_version display_value="sp_instance_9c23194e2f5b10108631f7ecf699b688">9c2315ce2f5b10108631f7ecf699b6c4</sys_update_version>
        <sys_updated_by>admin</sys_updated_by>
        <sys_updated_on>2020-09-18 07:44:50</sys_updated_on>
    </sys_metadata_delete>
</record_update>
