<?xml version="1.0" encoding="UTF-8"?><record_update table="sp_instance_menu">
    <sp_instance_menu action="DELETE">
        <active>true</active>
        <class_name/>
        <color>default</color>
        <css/>
        <glyph/>
        <id/>
        <order>1</order>
        <roles/>
        <short_description/>
        <size>md</size>
        <sp_column display_value="1">868cbd052f1310108631f7ecf699b6be</sp_column>
        <sp_widget display_value="Icon Menu List">88979930cb01020000f8d856634c9caa</sp_widget>
        <sys_class_name>sp_instance_menu</sys_class_name>
        <sys_created_by>admin</sys_created_by>
        <sys_created_on>2020-09-15 08:13:43</sys_created_on>
        <sys_id>cc0db5452f1310108631f7ecf699b635</sys_id>
        <sys_mod_count>0</sys_mod_count>
        <sys_name/>
        <sys_package display_value="ReisekostenabrechnungGr7" source="x_526619_reisekost">e45451372f031010e4c854492799b62b</sys_package>
        <sys_policy/>
        <sys_scope display_value="ReisekostenabrechnungGr7">e45451372f031010e4c854492799b62b</sys_scope>
        <sys_update_name>sp_instance_menu_cc0db5452f1310108631f7ecf699b635</sys_update_name>
        <sys_updated_by>admin</sys_updated_by>
        <sys_updated_on>2020-09-15 08:13:43</sys_updated_on>
        <title/>
        <url/>
        <widget_parameters/>
    </sp_instance_menu>
    <sys_translated_text action="DELETE" query="documentkey=cc0db5452f1310108631f7ecf699b635"/>
    <sys_update_version action="INSERT_OR_UPDATE">
        <action>DELETE</action>
        <application display_value="ReisekostenabrechnungGr7">e45451372f031010e4c854492799b62b</application>
        <file_path/>
        <instance_id>10a42f9fdb75c89452dd2f17d49619c2</instance_id>
        <instance_name>dev96488</instance_name>
        <name>sp_instance_menu_cc0db5452f1310108631f7ecf699b635</name>
        <payload><![CDATA[<?xml version="1.0" encoding="UTF-8"?><record_update table="sp_instance_menu"><sp_instance_menu action="INSERT_OR_UPDATE"><active>true</active><class_name/><color>default</color><css/><glyph/><id/><order>1</order><roles/><short_description/><size>md</size><sp_column display_value="1">868cbd052f1310108631f7ecf699b6be</sp_column><sp_widget display_value="Icon Menu List">88979930cb01020000f8d856634c9caa</sp_widget><sys_class_name>sp_instance_menu</sys_class_name><sys_created_by>admin</sys_created_by><sys_created_on>2020-09-15 08:13:43</sys_created_on><sys_id>cc0db5452f1310108631f7ecf699b635</sys_id><sys_mod_count>0</sys_mod_count><sys_name/><sys_package display_value="ReisekostenabrechnungGr7" source="x_526619_reisekost">e45451372f031010e4c854492799b62b</sys_package><sys_policy/><sys_scope display_value="ReisekostenabrechnungGr7">e45451372f031010e4c854492799b62b</sys_scope><sys_update_name>sp_instance_menu_cc0db5452f1310108631f7ecf699b635</sys_update_name><sys_updated_by>admin</sys_updated_by><sys_updated_on>2020-09-15 08:13:43</sys_updated_on><title/><url/><widget_parameters/></sp_instance_menu><sys_translated_text action="delete_multiple" query="documentkey=cc0db5452f1310108631f7ecf699b635"/></record_update>]]></payload>
        <payload_hash>-130461418</payload_hash>
        <record_name/>
        <reverted_from/>
        <source>4324bac82f1750108631f7ecf699b68b</source>
        <source_table>sys_update_set</source_table>
        <state>current</state>
        <sys_created_by>admin</sys_created_by>
        <sys_created_on>2020-09-15 08:13:44</sys_created_on>
        <sys_id>400db5452f1310108631f7ecf699b638</sys_id>
        <sys_mod_count>0</sys_mod_count>
        <sys_recorded_at>17490d3a6d10000001</sys_recorded_at>
        <sys_updated_by>admin</sys_updated_by>
        <sys_updated_on>2020-09-15 08:13:44</sys_updated_on>
        <type>Instance with Menu</type>
        <update_guid>880db545e9131010ef4f44f5cb889b37</update_guid>
        <update_guid_history>880db545e9131010ef4f44f5cb889b37:-130461418</update_guid_history>
    </sys_update_version>
    <sys_metadata_delete action="INSERT_OR_UPDATE">
        <sys_audit_delete display_value="">c8adfd452f1310108631f7ecf699b66d</sys_audit_delete>
        <sys_class_name>sys_metadata_delete</sys_class_name>
        <sys_created_by>admin</sys_created_by>
        <sys_created_on>2020-09-15 08:16:27</sys_created_on>
        <sys_db_object display_value="" name="sp_instance_menu">sp_instance_menu</sys_db_object>
        <sys_id>57acf52c97f64b2a8ce2d979b17f09a9</sys_id>
        <sys_metadata>cc0db5452f1310108631f7ecf699b635</sys_metadata>
        <sys_mod_count>0</sys_mod_count>
        <sys_name/>
        <sys_package display_value="ReisekostenabrechnungGr7" source="x_526619_reisekost">e45451372f031010e4c854492799b62b</sys_package>
        <sys_parent/>
        <sys_policy/>
        <sys_scope display_value="ReisekostenabrechnungGr7">e45451372f031010e4c854492799b62b</sys_scope>
        <sys_scope_delete display_value="">28719247fa724b2e8c95e64ffb1c1004</sys_scope_delete>
        <sys_update_name>sp_instance_menu_cc0db5452f1310108631f7ecf699b635</sys_update_name>
        <sys_update_version display_value="sp_instance_menu_cc0db5452f1310108631f7ecf699b635">400db5452f1310108631f7ecf699b638</sys_update_version>
        <sys_updated_by>admin</sys_updated_by>
        <sys_updated_on>2020-09-15 08:16:27</sys_updated_on>
    </sys_metadata_delete>
</record_update>
